<?xml version="1.0" encoding="UTF-8"?>
<persistence version="2.1" xmlns="http://xmlns.jcp.org/xml/ns/persistence" xmlns:xsi="http://www.w3.org/2001/XMLSchema-instance" xsi:schemaLocation="http://xmlns.jcp.org/xml/ns/persistence http://xmlns.jcp.org/xml/ns/persistence/persistence_2_1.xsd">
  <persistence-unit name="com.apu_TcpServerForAccessControl_jar_0.0.1-SNAPSHOTPU" transaction-type="RESOURCE_LOCAL">
    <provider>org.eclipse.persistence.jpa.PersistenceProvider</provider>
    <class>com.apu.TcpServerForAccessControl.entity.Rule</class>
    <class>com.apu.TcpServerForAccessControl.entity.EventType</class>
    <class>com.apu.TcpServerForAccessControl.entity.Device</class>
    <class>com.apu.TcpServerForAccessControl.entity.Card</class>
    <class>com.apu.TcpServerForAccessControl.entity.RulesType</class>
    <class>com.apu.TcpServerForAccessControl.entity.EventMessage</class>
    <class>com.apu.TcpServerForAccessControl.entity.AccessMessage</class>
    <class>com.apu.TcpServerForAccessControl.entity.AccessMessageWrong</class>
    <class>com.apu.TcpServerForAccessControl.entity.InfoMessage</class>
    <class>com.apu.TcpServerForAccessControl.entity.User</class>
    <!--     <properties> -->
    <!--       <property name="javax.persistence.jdbc.url" value="jdbc:mariadb://localhost:3306/accesscontroldb"/> -->
    <!--       <property name="javax.persistence.jdbc.user" value="app"/> -->
    <!--       <property name="javax.persistence.jdbc.driver" value="org.mariadb.jdbc.Driver"/> -->
    <!--       <property name="javax.persistence.jdbc.password" value="qwerty"/> -->
    <!--     </properties> -->    
  </persistence-unit>
</persistence>
